harp/__init__.py
harp/__main__.py
harp/_logging.py
harp/asgi/__init__.py
harp/asgi/bridge/__init__.py
harp/asgi/bridge/requests.py
harp/asgi/bridge/responses.py
harp/asgi/bridge/streams.py
harp/asgi/events.py
harp/asgi/kernel.py
harp/asgi/tests/__init__.py
harp/asgi/tests/test_http_bridge_asgi_request.py
harp/commandline/__init__.py
harp/commandline/config.py
harp/commandline/cookiecutters/__init__.py
harp/commandline/cookiecutters/project/LICENSE
harp/commandline/cookiecutters/project/README.rst
harp/commandline/cookiecutters/project/__init__.py
harp/commandline/cookiecutters/project/cookiecutter.json
harp/commandline/cookiecutters/project/hooks/post_gen_project.sh
harp/commandline/cookiecutters/project/{{cookiecutter.__dir_name}}/Makefile
harp/commandline/cookiecutters/project/{{cookiecutter.__dir_name}}/README.rst
harp/commandline/cookiecutters/project/{{cookiecutter.__dir_name}}/__init__.py
harp/commandline/cookiecutters/project/{{cookiecutter.__dir_name}}/config.yml
harp/commandline/cookiecutters/project/{{cookiecutter.__dir_name}}/pyproject.toml
harp/commandline/cookiecutters/project/{{cookiecutter.__dir_name}}/tests/conftest.py
harp/commandline/cookiecutters/project/{{cookiecutter.__dir_name}}/tests/test_e2e.py
harp/commandline/cookiecutters/project/{{cookiecutter.__dir_name}}/{{cookiecutter.__pkg_name}}/__app__.py
harp/commandline/cookiecutters/project/{{cookiecutter.__dir_name}}/{{cookiecutter.__pkg_name}}/__init__.py
harp/commandline/create.py
harp/commandline/examples.py
harp/commandline/install.py
harp/commandline/migrations.py
harp/commandline/options/__init__.py
harp/commandline/options/server.py
harp/commandline/server.py
harp/commandline/start.py
harp/commandline/tests/__init__.py
harp/commandline/tests/__snapshots__/test_examples_commands.ambr
harp/commandline/tests/test_examples_commands.py
harp/commandline/tests/test_options_server.py
harp/commandline/utils/__init__.py
harp/commandline/utils/_hacks.py
harp/commandline/utils/manager.py
harp_proxy-0.8.1.dist-info/LICENSE.rst
harp_proxy-0.8.1.dist-info/METADATA
harp_proxy-0.8.1.dist-info/WHEEL
harp_proxy-0.8.1.dist-info/entry_points.txt
harp_proxy-0.8.1.dist-info/RECORD
