Metadata-Version: 2.1
Name: harp-proxy
Version: 0.8.1
Summary: Harp is an API Runtime Proxy – A toolkit for Fast, Reliable and Observable external APIs
Author: Romain Dorgueil
Author-email: romain@makersquad.fr
Requires-Python: >=3.12,<3.13
Classifier: Programming Language :: Python :: 3
Classifier: Programming Language :: Python :: 3.12
Provides-Extra: dev
Requires-Dist: aiohttp (>=3.11,<3.12)
Requires-Dist: aiosqlite (>=0.20,<0.22)
Requires-Dist: alembic (>=1.14,<1.16)
Requires-Dist: anyio (>=4.6,<4.10)
Requires-Dist: asgi-prometheus (>=1.2,<1.3)
Requires-Dist: asgi-tools (>=1.1,<1.2)
Requires-Dist: asgimiddlewarestaticfile (>=0.6,<0.7)
Requires-Dist: asgiref (>=3.8,<3.9)
Requires-Dist: asyncpg (>=0.30,<0.31)
Requires-Dist: colorama (>=0.4,<0.5)
Requires-Dist: cookiecutter (>=2.6,<2.7) ; extra == "dev"
Requires-Dist: dataclasses-json (>=0.6,<0.7)
Requires-Dist: dataclasses-jsonschema (>=2.16,<2.17)
Requires-Dist: essentials-configuration (>=2.0,<2.1)
Requires-Dist: hishel (>=0.1.1,<0.2.0)
Requires-Dist: honcho (>=2.0,<2.1) ; extra == "dev"
Requires-Dist: http-router (>=5.0,<5.1)
Requires-Dist: httpx (>=0.27,<0.29)
Requires-Dist: hypercorn (>=0.17,<0.18)
Requires-Dist: multidict (>=6.1,<6.3)
Requires-Dist: orjson (>=3.10,<3.11)
Requires-Dist: passlib (>=1.7,<1.8)
Requires-Dist: psycopg2-binary (>=2.9,<2.10)
Requires-Dist: pydantic (>=2.9,<2.12)
Requires-Dist: pyheck (>=0.1,<0.2)
Requires-Dist: pyyaml (>=6.0,<6.1)
Requires-Dist: redis (>=5.2,<5.3)
Requires-Dist: rich (>=13.9,<14.0)
Requires-Dist: rich-click (>=1.8,<1.9)
Requires-Dist: rodi (>=2.0,<2.1)
Requires-Dist: sentry-sdk (>=2.18,<3.0)
Requires-Dist: slack-sdk (>=3.33,<3.36)
Requires-Dist: sqlalchemy-utils (>=0.41,<0.42)
Requires-Dist: sqlalchemy[asyncio] (>=2.0,<2.1)
Requires-Dist: structlog (>=24.4,<25.3)
Requires-Dist: svix-ksuid (>=0.6,<0.7)
Requires-Dist: watchfiles (>=0.24,<1.1) ; extra == "dev"
Requires-Dist: whistle (>=2.0.1,<3.0.0)
